{"rewiredVersion":{"version1":1,"version2":1,"version3":14,"version4":4,"unityVersion":"U2018"},"userData":{"configVars":{"updateLoop":{"value__":1},"alwaysUseUnityInput":false,"windowsStandalonePrimaryInputSource":{"value__":0},"osx_primaryInputSource":{"value__":0},"linux_primaryInputSource":{"value__":0},"windowsUWP_primaryInputSource":{"value__":0},"xboxOne_primaryInputSource":{"value__":0},"ps4_primaryInputSource":{"value__":0},"webGL_primaryInputSource":{"value__":0},"useXInput":true,"useNativeMouse":true,"useEnhancedDeviceSupport":true,"windowsStandalone_useSteamRawInputControllerWorkaround":false,"osxStandalone_useEnhancedDeviceSupport":true,"android_supportUnknownGamepads":true,"ps4_assignJoysticksByPS4JoyId":true,"useSteamControllerSupport":true,"logToScreen":false,"platformVars_windowsStandalone":{"useNativeKeyboard":true,"joystickRefreshRate":240,"disableKeyboard":false,"ignoreInputWhenAppNotInFocus":true},"platformVars_linuxStandalone":{"disableKeyboard":false,"ignoreInputWhenAppNotInFocus":true},"platformVars_osxStandalone":{"disableKeyboard":false,"ignoreInputWhenAppNotInFocus":true},"platformVars_windows8Store":{"disableKeyboard":false,"ignoreInputWhenAppNotInFocus":true},"platformVars_windowsUWP":{"useGamepadAPI":true,"useHIDAPI":true,"disableKeyboard":false,"ignoreInputWhenAppNotInFocus":true},"platformVars_iOS":{"disableKeyboard":false,"ignoreInputWhenAppNotInFocus":true},"platformVars_tvOS":{"disableKeyboard":false,"ignoreInputWhenAppNotInFocus":true},"platformVars_android":{"disableKeyboard":false,"ignoreInputWhenAppNotInFocus":true},"platformVars_ps3":{"disableKeyboard":false,"ignoreInputWhenAppNotInFocus":true},"platformVars_ps4":{"disableKeyboard":false,"ignoreInputWhenAppNotInFocus":true},"platformVars_psVita":{"disableKeyboard":false,"ignoreInputWhenAppNotInFocus":true},"platformVars_xbox360":{"disableKeyboard":false,"ignoreInputWhenAppNotInFocus":true},"platformVars_xboxOne":{"disableKeyboard":false,"ignoreInputWhenAppNotInFocus":true},"platformVars_wii":{"disableKeyboard":false,"ignoreInputWhenAppNotInFocus":true},"platformVars_wiiu":{"disableKeyboard":false,"ignoreInputWhenAppNotInFocus":true},"platformVars_switch":{"disableKeyboard":false,"ignoreInputWhenAppNotInFocus":true},"platformVars_webGL":{"disableKeyboard":false,"ignoreInputWhenAppNotInFocus":true},"maxJoysticksPerPlayer":1,"autoAssignJoysticks":true,"assignJoysticksToPlayingPlayersOnly":false,"distributeJoysticksEvenly":true,"reassignJoystickToPreviousOwnerOnReconnect":true,"defaultJoystickAxis2DDeadZoneType":{"value__":1},"force4WayHats":false,"throttleCalibrationMode":{"value__":0},"deferControllerConnectedEventsOnStart":false,"logLevel":{"value__":-1},"editorSettings":{"exportConsts_useParentClass":false,"exportConsts_parentClassName":"RewiredConsts","exportConsts_useNamespace":true,"exportConsts_namespace":"RewiredConsts","exportConsts_actions":true,"exportConsts_actionsClassName":"Action","exportConsts_actionsIncludeActionCategory":false,"exportConsts_actionsCreateClassesForActionCategories":false,"exportConsts_mapCategories":true,"exportConsts_mapCategoriesClassName":"Category","exportConsts_layouts":true,"exportConsts_layoutsClassName":"Layout","exportConsts_players":true,"exportConsts_playersClassName":"Player","exportConsts_customControllers":true,"exportConsts_customControllersClassName":"CustomController","exportConsts_customControllersAxesClassName":"Axis","exportConsts_customControllersButtonsClassName":"Button","exportConsts_allCapsConstantNames":false}},"players":[{"_id":9999999,"_name":"System","_descriptiveName":"System","_startPlaying":true,"_defaultJoystickMaps":[],"_defaultMouseMaps":[],"_defaultKeyboardMaps":[],"_defaultCustomControllerMaps":[],"_startingCustomControllers":[],"_assignMouseOnStart":true,"_assignKeyboardOnStart":true,"_excludeFromControllerAutoAssignment":true,"id":9999999,"name":"System","descriptiveName":"System","startPlaying":true,"defaultJoystickMaps":[],"defaultMouseMaps":[],"defaultKeyboardMaps":[],"defaultCustomControllerMaps":[],"startingCustomControllers":[],"assignMouseOnStart":true,"assignKeyboardOnStart":true,"excludeFromControllerAutoAssignment":true},{"_id":1,"_name":"Player0","_descriptiveName":"Player0","_startPlaying":true,"_defaultJoystickMaps":[{"_enabled":true,"_categoryId":0,"_layoutId":0,"categoryId":0,"layoutId":0,"enabled":true}],"_defaultMouseMaps":[],"_defaultKeyboardMaps":[{"_enabled":true,"_categoryId":0,"_layoutId":0,"categoryId":0,"layoutId":0,"enabled":true}],"_defaultCustomControllerMaps":[],"_startingCustomControllers":[],"_assignMouseOnStart":true,"_assignKeyboardOnStart":true,"_excludeFromControllerAutoAssignment":false,"id":1,"name":"Player0","descriptiveName":"Player0","startPlaying":true,"defaultJoystickMaps":[{"_enabled":true,"_categoryId":0,"_layoutId":0,"categoryId":0,"layoutId":0,"enabled":true}],"defaultMouseMaps":[],"defaultKeyboardMaps":[{"_enabled":true,"_categoryId":0,"_layoutId":0,"categoryId":0,"layoutId":0,"enabled":true}],"defaultCustomControllerMaps":[],"startingCustomControllers":[],"assignMouseOnStart":true,"assignKeyboardOnStart":true,"excludeFromControllerAutoAssignment":false}],"actions":[{"_id":0,"_name":"Move","_type":{"value__":0},"_descriptiveName":"Move","_positiveDescriptiveName":"Walk Right","_negativeDescriptiveName":"Walk Left","_behaviorId":0,"_userAssignable":true,"_categoryId":1,"id":0,"name":"Move","type":{"value__":0},"descriptiveName":"Move","positiveDescriptiveName":"Walk Right","negativeDescriptiveName":"Walk Left","behaviorId":0,"categoryId":1,"userAssignable":true},{"_id":2,"_name":"Hop","_type":{"value__":1},"_descriptiveName":"Hop","_positiveDescriptiveName":"","_negativeDescriptiveName":"","_behaviorId":0,"_userAssignable":true,"_categoryId":1,"id":2,"name":"Hop","type":{"value__":1},"descriptiveName":"Hop","positiveDescriptiveName":"","negativeDescriptiveName":"","behaviorId":0,"categoryId":1,"userAssignable":true},{"_id":4,"_name":"Crouch","_type":{"value__":0},"_descriptiveName":"Crouch","_positiveDescriptiveName":"","_negativeDescriptiveName":"Crouch","_behaviorId":0,"_userAssignable":true,"_categoryId":1,"id":4,"name":"Crouch","type":{"value__":0},"descriptiveName":"Crouch","positiveDescriptiveName":"","negativeDescriptiveName":"Crouch","behaviorId":0,"categoryId":1,"userAssignable":true},{"_id":5,"_name":"Neutral","_type":{"value__":1},"_descriptiveName":"Neutral","_positiveDescriptiveName":"","_negativeDescriptiveName":"","_behaviorId":0,"_userAssignable":true,"_categoryId":2,"id":5,"name":"Neutral","type":{"value__":1},"descriptiveName":"Neutral","positiveDescriptiveName":"","negativeDescriptiveName":"","behaviorId":0,"categoryId":2,"userAssignable":true},{"_id":16,"_name":"Strong","_type":{"value__":0},"_descriptiveName":"Strong","_positiveDescriptiveName":"Up Strong","_negativeDescriptiveName":"Down Strong","_behaviorId":0,"_userAssignable":true,"_categoryId":2,"id":16,"name":"Strong","type":{"value__":0},"descriptiveName":"Strong","positiveDescriptiveName":"Up Strong","negativeDescriptiveName":"Down Strong","behaviorId":0,"categoryId":2,"userAssignable":true},{"_id":19,"_name":"Special","_type":{"value__":1},"_descriptiveName":"Special","_positiveDescriptiveName":"","_negativeDescriptiveName":"","_behaviorId":0,"_userAssignable":true,"_categoryId":2,"id":19,"name":"Special","type":{"value__":1},"descriptiveName":"Special","positiveDescriptiveName":"","negativeDescriptiveName":"","behaviorId":0,"categoryId":2,"userAssignable":true},{"_id":22,"_name":"Shield","_type":{"value__":1},"_descriptiveName":"Shield","_positiveDescriptiveName":"","_negativeDescriptiveName":"","_behaviorId":0,"_userAssignable":true,"_categoryId":3,"id":22,"name":"Shield","type":{"value__":1},"descriptiveName":"Shield","positiveDescriptiveName":"","negativeDescriptiveName":"","behaviorId":0,"categoryId":3,"userAssignable":true},{"_id":23,"_name":"Grab","_type":{"value__":1},"_descriptiveName":"Grab","_positiveDescriptiveName":"","_negativeDescriptiveName":"","_behaviorId":0,"_userAssignable":true,"_categoryId":3,"id":23,"name":"Grab","type":{"value__":1},"descriptiveName":"Grab","positiveDescriptiveName":"","negativeDescriptiveName":"","behaviorId":0,"categoryId":3,"userAssignable":true}],"actionCategories":[{"_name":"Default","_descriptiveName":"Default","_tag":"","_id":0,"_userAssignable":true,"name":"Default","descriptiveName":"Default","tag":"","id":0,"userAssignable":true},{"_name":"Movement","_descriptiveName":"Movement Actions","_tag":"","_id":1,"_userAssignable":true,"name":"Movement","descriptiveName":"Movement Actions","tag":"","id":1,"userAssignable":true},{"_name":"Attacks","_descriptiveName":"Attack Actions","_tag":"","_id":2,"_userAssignable":true,"name":"Attacks","descriptiveName":"Attack Actions","tag":"","id":2,"userAssignable":true},{"_name":"DefensiveOptions","_descriptiveName":"Defensive Options","_tag":"","_id":3,"_userAssignable":true,"name":"DefensiveOptions","descriptiveName":"Defensive Options","tag":"","id":3,"userAssignable":true}],"actionCategoryMap":{"list":[{"categoryId":0,"actionIds":[]},{"categoryId":1,"actionIds":[0,2,4]},{"categoryId":2,"actionIds":[5,19,16]},{"categoryId":3,"actionIds":[22,23]}]},"inputBehaviors":[{"_id":0,"_name":"Default","_joystickAxisSensitivity":1,"_digitalAxisSimulation":true,"_digitalAxisSnap":true,"_digitalAxisInstantReverse":false,"_digitalAxisGravity":3,"_digitalAxisSensitivity":3,"_mouseXYAxisMode":{"value__":0},"_mouseOtherAxisMode":{"value__":0},"_mouseXYAxisSensitivity":1,"_mouseXYAxisDeltaCalc":{"value__":0},"_mouseOtherAxisSensitivity":1,"_customControllerAxisSensitivity":1,"_buttonDoublePressSpeed":0.3,"_buttonShortPressTime":0,"_buttonShortPressExpiresIn":0,"_buttonLongPressTime":0.1,"_buttonLongPressExpiresIn":0,"_buttonDeadZone":0.5,"_buttonDownBuffer":0,"_buttonRepeatRate":30,"_buttonRepeatDelay":0,"id":0,"name":"Default","joystickAxisSensitivity":1,"digitalAxisSimulation":true,"digitalAxisSnap":true,"digitalAxisInstantReverse":false,"digitalAxisGravity":3,"digitalAxisSensitivity":3,"mouseXYAxisMode":{"value__":0},"mouseOtherAxisMode":{"value__":0},"mouseXYAxisSensitivity":1,"mouseXYAxisDeltaCalc":{"value__":0},"mouseOtherAxisSensitivity":1,"customControllerAxisSensitivity":1,"buttonDoublePressSpeed":0.3,"buttonShortPressTime":0,"buttonShortPressExpiresIn":0,"buttonLongPressTime":0.1,"buttonLongPressExpiresIn":0,"buttonDeadZone":0.5,"buttonDownBuffer":0,"buttonRepeatRate":30,"buttonRepeatDelay":0}],"mapCategories":[{"_checkConflictsWithAllCategories":true,"_checkConflictsCategoryIds":[],"_name":"Default","_descriptiveName":"Default","_tag":"","_id":0,"_userAssignable":true,"checkConflictsWithAllCategories":true,"name":"Default","descriptiveName":"Default","tag":"","id":0,"userAssignable":true}],"joystickLayouts":[{"_name":"Default","_descriptiveName":"Default","_id":0,"name":"Default","descriptiveName":"Default","id":0}],"keyboardLayouts":[{"_name":"Default","_descriptiveName":"Default","_id":0,"name":"Default","descriptiveName":"Default","id":0}],"mouseLayouts":[{"_name":"Default","_descriptiveName":"Default","_id":0,"name":"Default","descriptiveName":"Default","id":0}],"customControllerLayouts":[{"_name":"Default","_descriptiveName":"Default","_id":0,"name":"Default","descriptiveName":"Default","id":0}],"joystickMaps":[{"id":0,"categoryId":0,"layoutId":0,"name":"","hardwareGuidString":"83b427e4-086f-47f3-bb06-be266abd1ca5","customControllerUid":0,"actionElementMaps":[{"_actionCategoryId":0,"_actionId":0,"_elementType":{"value__":0},"_elementIdentifierId":0,"_axisRange":{"value__":0},"_invert":false,"_axisContribution":{"value__":0},"_keyboardKeyCode":{"value__":0},"_modifierKey1":{"value__":0},"_modifierKey2":{"value__":0},"_modifierKey3":{"value__":0},"actionId":0,"elementType":{"value__":0},"elementIdentifierId":0,"axisRange":{"value__":0},"invert":false,"axisContribution":{"value__":0},"keyboardKeyCode":{"value__":0},"modifierKey1":{"value__":0},"modifierKey2":{"value__":0},"modifierKey3":{"value__":0},"enabled":true,"elementIndex":0},{"_actionCategoryId":0,"_actionId":4,"_elementType":{"value__":0},"_elementIdentifierId":1,"_axisRange":{"value__":0},"_invert":false,"_axisContribution":{"value__":0},"_keyboardKeyCode":{"value__":0},"_modifierKey1":{"value__":0},"_modifierKey2":{"value__":0},"_modifierKey3":{"value__":0},"actionId":4,"elementType":{"value__":0},"elementIdentifierId":1,"axisRange":{"value__":0},"invert":false,"axisContribution":{"value__":0},"keyboardKeyCode":{"value__":0},"modifierKey1":{"value__":0},"modifierKey2":{"value__":0},"modifierKey3":{"value__":0},"enabled":true,"elementIndex":0},{"_actionCategoryId":0,"_actionId":2,"_elementType":{"value__":1},"_elementIdentifierId":8,"_axisRange":{"value__":0},"_invert":false,"_axisContribution":{"value__":0},"_keyboardKeyCode":{"value__":0},"_modifierKey1":{"value__":0},"_modifierKey2":{"value__":0},"_modifierKey3":{"value__":0},"actionId":2,"elementType":{"value__":1},"elementIdentifierId":8,"axisRange":{"value__":0},"invert":false,"axisContribution":{"value__":0},"keyboardKeyCode":{"value__":0},"modifierKey1":{"value__":0},"modifierKey2":{"value__":0},"modifierKey3":{"value__":0},"enabled":true,"elementIndex":0},{"_actionCategoryId":0,"_actionId":2,"_elementType":{"value__":1},"_elementIdentifierId":7,"_axisRange":{"value__":0},"_invert":false,"_axisContribution":{"value__":0},"_keyboardKeyCode":{"value__":0},"_modifierKey1":{"value__":0},"_modifierKey2":{"value__":0},"_modifierKey3":{"value__":0},"actionId":2,"elementType":{"value__":1},"elementIdentifierId":7,"axisRange":{"value__":0},"invert":false,"axisContribution":{"value__":0},"keyboardKeyCode":{"value__":0},"modifierKey1":{"value__":0},"modifierKey2":{"value__":0},"modifierKey3":{"value__":0},"enabled":true,"elementIndex":0},{"_actionCategoryId":0,"_actionId":19,"_elementType":{"value__":1},"_elementIdentifierId":4,"_axisRange":{"value__":0},"_invert":false,"_axisContribution":{"value__":0},"_keyboardKeyCode":{"value__":0},"_modifierKey1":{"value__":0},"_modifierKey2":{"value__":0},"_modifierKey3":{"value__":0},"actionId":19,"elementType":{"value__":1},"elementIdentifierId":4,"axisRange":{"value__":0},"invert":false,"axisContribution":{"value__":0},"keyboardKeyCode":{"value__":0},"modifierKey1":{"value__":0},"modifierKey2":{"value__":0},"modifierKey3":{"value__":0},"enabled":true,"elementIndex":0},{"_actionCategoryId":0,"_actionId":5,"_elementType":{"value__":1},"_elementIdentifierId":6,"_axisRange":{"value__":0},"_invert":false,"_axisContribution":{"value__":0},"_keyboardKeyCode":{"value__":0},"_modifierKey1":{"value__":0},"_modifierKey2":{"value__":0},"_modifierKey3":{"value__":0},"actionId":5,"elementType":{"value__":1},"elementIdentifierId":6,"axisRange":{"value__":0},"invert":false,"axisContribution":{"value__":0},"keyboardKeyCode":{"value__":0},"modifierKey1":{"value__":0},"modifierKey2":{"value__":0},"modifierKey3":{"value__":0},"enabled":true,"elementIndex":0},{"_actionCategoryId":0,"_actionId":23,"_elementType":{"value__":1},"_elementIdentifierId":10,"_axisRange":{"value__":0},"_invert":false,"_axisContribution":{"value__":0},"_keyboardKeyCode":{"value__":0},"_modifierKey1":{"value__":0},"_modifierKey2":{"value__":0},"_modifierKey3":{"value__":0},"actionId":23,"elementType":{"value__":1},"elementIdentifierId":10,"axisRange":{"value__":0},"invert":false,"axisContribution":{"value__":0},"keyboardKeyCode":{"value__":0},"modifierKey1":{"value__":0},"modifierKey2":{"value__":0},"modifierKey3":{"value__":0},"enabled":true,"elementIndex":0},{"_actionCategoryId":0,"_actionId":22,"_elementType":{"value__":1},"_elementIdentifierId":12,"_axisRange":{"value__":0},"_invert":false,"_axisContribution":{"value__":0},"_keyboardKeyCode":{"value__":0},"_modifierKey1":{"value__":0},"_modifierKey2":{"value__":0},"_modifierKey3":{"value__":0},"actionId":22,"elementType":{"value__":1},"elementIdentifierId":12,"axisRange":{"value__":0},"invert":false,"axisContribution":{"value__":0},"keyboardKeyCode":{"value__":0},"modifierKey1":{"value__":0},"modifierKey2":{"value__":0},"modifierKey3":{"value__":0},"enabled":true,"elementIndex":0}]}],"keyboardMaps":[{"id":0,"categoryId":0,"layoutId":0,"name":"","hardwareGuidString":"","customControllerUid":0,"actionElementMaps":[{"_actionCategoryId":0,"_actionId":0,"_elementType":{"value__":1},"_elementIdentifierId":-1,"_axisRange":{"value__":0},"_invert":false,"_axisContribution":{"value__":1},"_keyboardKeyCode":{"value__":97},"_modifierKey1":{"value__":0},"_modifierKey2":{"value__":0},"_modifierKey3":{"value__":0},"actionId":0,"elementType":{"value__":1},"elementIdentifierId":-1,"axisRange":{"value__":0},"invert":false,"axisContribution":{"value__":1},"keyboardKeyCode":{"value__":97},"modifierKey1":{"value__":0},"modifierKey2":{"value__":0},"modifierKey3":{"value__":0},"enabled":true,"elementIndex":0},{"_actionCategoryId":0,"_actionId":0,"_elementType":{"value__":1},"_elementIdentifierId":-1,"_axisRange":{"value__":0},"_invert":false,"_axisContribution":{"value__":0},"_keyboardKeyCode":{"value__":100},"_modifierKey1":{"value__":0},"_modifierKey2":{"value__":0},"_modifierKey3":{"value__":0},"actionId":0,"elementType":{"value__":1},"elementIdentifierId":-1,"axisRange":{"value__":0},"invert":false,"axisContribution":{"value__":0},"keyboardKeyCode":{"value__":100},"modifierKey1":{"value__":0},"modifierKey2":{"value__":0},"modifierKey3":{"value__":0},"enabled":true,"elementIndex":0}]}],"mouseMaps":[],"customControllerMaps":[],"customControllers":[],"playerIdCounter":2,"actionIdCounter":24,"actionCategoryIdCounter":4,"inputBehaviorIdCounter":5,"mapCategoryIdCounter":1,"joystickLayoutIdCounter":1,"keyboardLayoutIdCounter":1,"mouseLayoutIdCounter":1,"customControllerLayoutIdCounter":1,"joystickMapIdCounter":1,"keyboardMapIdCounter":1,"mouseMapIdCounter":0,"customControllerMapIdCounter":0,"customControllerIdCounter":0}}